CHANGES.txt
LICENSE.txt
MANIFEST.in
README.md
setup.py
dhclientlist/__init__.py
dhclientlist/__main__.py
dhclientlist/util.py
dhclientlist.egg-info/PKG-INFO
dhclientlist.egg-info/SOURCES.txt
dhclientlist.egg-info/dependency_links.txt
dhclientlist.egg-info/requires.txt
dhclientlist.egg-info/top_level.txt
dhclientlist/drivers/__init__.py
dhclientlist/drivers/tp_link/__init__.py
dhclientlist/drivers/tp_link/generic.py
dhclientlist/server/__init__.py
dhclientlist/server/application.py
dhclientlist/server/settings.py
scripts/dhclientlist