Metadata-Version: 1.0
Name: dhclientlist
Version: 0.0.6
Summary: DHClientList is a tool to get the current client list of a DHCP server. With it one can check who is connected to the local network. To do this one must provide the DHCP server address (IP in local network and port), username and password. The resulting list items contains the host name, MAC address, IP and lease time.
Home-page: https://github.com/leonardosantos/dhclientlist
Author: Leonardo Santos
Author-email: lsantos@inoa.com.br
License: LICENSE.txt
Platform: UNKNOWN
Classifier: Development Status :: 4 - Beta
Classifier: Intended Audience :: Developers
Classifier: Topic :: Utilities
Classifier: License :: OSI Approved :: BSD License
